pytree/__init__.py
pytree/main.py
pytree/main_loc.py
pytree/classes/ProgressTracker.py
pytree/classes/PyTree.py
pytree/classes/__init__.py
pytree/utils/__init__.py
pytree/utils/aux_funcs.py
pytree/utils/global_vars.py
pytree2-0.2.2.dist-info/licenses/LICENSE.md
pytree2-0.2.2.dist-info/METADATA
pytree2-0.2.2.dist-info/WHEEL
pytree2-0.2.2.dist-info/entry_points.txt
pytree2-0.2.2.dist-info/top_level.txt
pytree2-0.2.2.dist-info/RECORD
