Metadata-Version: 2.4
Name: pytree2
Version: 0.2.2
Summary: A Python CLI utility for visualizing folder trees with sizes and counts.
Author-email: Angelo Luiz Angonezi <angeloangonezi2@gmail.com>
License-Expression: MIT
Project-URL: Homepage, https://github.com/angelo-angonezi/pytree
Project-URL: Issues, https://github.com/angelo-angonezi/pytree/issues
Keywords: python,cli,tree,folder structure,file size,disk usage
Requires-Python: >=3.8
License-File: LICENSE.md
Requires-Dist: treelib
Dynamic: license-file
